ansible_vault_var/__init__.py
ansible_vault_var/__main__.py
ansible_vault_var/cli.py
ansible_vault_var/console.py
ansible_vault_var/tool.py
ansible_vault_var/vars_yaml.py
ansible_vault_var-1.0.1.dist-info/METADATA
ansible_vault_var-1.0.1.dist-info/WHEEL
ansible_vault_var-1.0.1.dist-info/namespace_packages.txt
ansible_vault_var-1.0.1.dist-info/top_level.txt
ansible_vault_var-1.0.1.dist-info/RECORD
