Metadata-Version: 2.1
Name: ansible-vault-var
Version: 1.0.1
Summary: Get and set encrypted values in vars yaml file.
Home-page: https://github.com/cbuschka/ansible-vault-var
Author: Cornelius Buschka
Author-email: cbuschka@gmail.com
License: MIT License
Platform: Posix; MacOS X
Classifier: Development Status :: 5 - Production/Stable
Classifier: Intended Audience :: Developers
Classifier: License :: OSI Approved :: MIT License
Classifier: Operating System :: OS Independent
Classifier: Programming Language :: Python :: 3
Classifier: Programming Language :: Python :: 3.6
Classifier: Programming Language :: Python :: 3.7
Classifier: Programming Language :: Python :: 3.8
Classifier: Programming Language :: Python :: 3.9
Classifier: Topic :: System :: Software Distribution
Requires-Python: >= 3.6
Requires-Dist: ansible (>=2.9.0)
